// 
// Decompiled by Procyon v0.6-prerelease
// 

package com.admarvel.android.ads;

import com.admarvel.android.util.Logging;
import android.util.Log;
import android.content.Context;
import java.lang.ref.WeakReference;
import java.text.SimpleDateFormat;

class r$d implements Runnable
{
    SimpleDateFormat a;
    Long b;
    Long c;
    String d;
    String e;
    String f;
    String g;
    String h;
    String i;
    int j;
    private final WeakReference k;
    private final WeakReference l;
    
    public r$d(final d d, final Context context, final String s, final String d2, final String e) {
        this.a = new SimpleDateFormat("yyyyMMddhhmm");
        this.b = null;
        this.c = null;
        this.j = 1;
        this.k = new WeakReference((T)context);
        this.l = new WeakReference((T)d);
        Label_0100: {
            if (s == null) {
                break Label_0100;
            }
            try {
                this.b = this.a.parse(s).getTime();
                this.c = this.a.parse(s).getTime() + 3600000L;
                this.d = d2;
                this.e = e;
            }
            catch (Exception ex) {
                Logging.log(Log.getStackTraceString((Throwable)ex));
            }
        }
    }
    
    public r$d(final d d, final Context context, final String s, final String d2, final String e, final String f, final String g, final String s2, final int n) {
        this.a = new SimpleDateFormat("yyyyMMddhhmm");
        this.b = null;
        this.c = null;
        this.j = 1;
        this.k = new WeakReference((T)context);
        this.l = new WeakReference((T)d);
        while (true) {
            if (s != null) {
                try {
                    this.b = this.a.parse(s).getTime();
                    if (s2 != null) {
                        this.c = this.a.parse(s2).getTime();
                    }
                    else {
                        this.c = this.a.parse(s).getTime() + 3600000L;
                    }
                    this.d = d2;
                    this.e = e;
                    this.f = f;
                    this.g = g;
                    if (n <= 0) {
                        this.j = n / 60;
                    }
                }
                catch (Exception ex) {
                    ex.printStackTrace();
                }
                return;
            }
            continue;
        }
    }
    
    public r$d(final d d, final Context context, final String s, final String d2, final String e, final String f, final String g, final String s2, final int n, final String h, final String s3, final String s4, final String s5, final int n2, final int n3, final String i) {
        this.a = new SimpleDateFormat("yyyyMMddhhmm");
        this.b = null;
        this.c = null;
        this.j = 1;
        this.k = new WeakReference((T)context);
        this.l = new WeakReference((T)d);
        Label_0078: {
            if (s == null) {
                break Label_0078;
            }
            try {
                this.b = this.a.parse(s).getTime();
                if (s2 != null) {
                    this.c = this.a.parse(s2).getTime();
                }
                else {
                    this.c = this.a.parse(s).getTime() + 3600000L;
                }
                this.d = d2;
                this.e = e;
                this.f = f;
                this.g = g;
                if (n <= 0) {
                    this.j = n / 60;
                }
                if (h != null && h.length() > 0) {
                    this.h = h;
                }
                this.i = i;
            }
            catch (Exception ex) {
                ex.printStackTrace();
            }
        }
    }
    
    String a() {
        if (Version.getAndroidSDKVersion() >= 8) {
            return "content://com.android.calendar/";
        }
        return "content://calendar/";
    }
    
    @Override
    public void run() {
        // 
        // This method could not be decompiled.
        // 
        // Original Bytecode:
        // 
        //     1: getfield        com/admarvel/android/ads/r$d.k:Ljava/lang/ref/WeakReference;
        //     4: invokevirtual   java/lang/ref/WeakReference.get:()Ljava/lang/Object;
        //     7: checkcast       Landroid/content/Context;
        //    10: astore_2       
        //    11: aload_0        
        //    12: getfield        com/admarvel/android/ads/r$d.l:Ljava/lang/ref/WeakReference;
        //    15: invokevirtual   java/lang/ref/WeakReference.get:()Ljava/lang/Object;
        //    18: checkcast       Lcom/admarvel/android/ads/d;
        //    21: astore          5
        //    23: aload_2        
        //    24: ifnull          32
        //    27: aload           5
        //    29: ifnonnull       33
        //    32: return         
        //    33: aload_2        
        //    34: invokevirtual   android/content/Context.getContentResolver:()Landroid/content/ContentResolver;
        //    37: astore          4
        //    39: aload           4
        //    41: new             Ljava/lang/StringBuilder;
        //    44: dup            
        //    45: invokespecial   java/lang/StringBuilder.<init>:()V
        //    48: aload_0        
        //    49: invokevirtual   com/admarvel/android/ads/r$d.a:()Ljava/lang/String;
        //    52: invokevirtual   java/lang/StringBuilder.append:(Ljava/lang/String;)Ljava/lang/StringBuilder;
        //    55: ldc             "calendars"
        //    57: invokevirtual   java/lang/StringBuilder.append:(Ljava/lang/String;)Ljava/lang/StringBuilder;
        //    60: invokevirtual   java/lang/StringBuilder.toString:()Ljava/lang/String;
        //    63: invokestatic    android/net/Uri.parse:(Ljava/lang/String;)Landroid/net/Uri;
        //    66: iconst_2       
        //    67: anewarray       Ljava/lang/String;
        //    70: dup            
        //    71: iconst_0       
        //    72: ldc             "_id"
        //    74: aastore        
        //    75: dup            
        //    76: iconst_1       
        //    77: ldc             "displayname"
        //    79: aastore        
        //    80: aconst_null    
        //    81: aconst_null    
        //    82: aconst_null    
        //    83: invokevirtual   android/content/ContentResolver.query:(Landroid/net/Uri;[Ljava/lang/String;Ljava/lang/String;[Ljava/lang/String;Ljava/lang/String;)Landroid/database/Cursor;
        //    86: astore_3       
        //    87: aload_3        
        //    88: ifnull          639
        //    91: aload_3        
        //    92: astore_2       
        //    93: aload_3        
        //    94: invokeinterface android/database/Cursor.moveToFirst:()Z
        //    99: ifeq            639
        //   102: aload_3        
        //   103: astore_2       
        //   104: aload_3        
        //   105: invokeinterface android/database/Cursor.getCount:()I
        //   110: anewarray       Ljava/lang/String;
        //   113: astore          7
        //   115: aload_3        
        //   116: astore_2       
        //   117: aload_3        
        //   118: invokeinterface android/database/Cursor.getCount:()I
        //   123: newarray        I
        //   125: astore          6
        //   127: iconst_0       
        //   128: istore_1       
        //   129: aload_3        
        //   130: astore_2       
        //   131: iload_1        
        //   132: aload           7
        //   134: arraylength    
        //   135: if_icmpge       180
        //   138: aload_3        
        //   139: astore_2       
        //   140: aload           6
        //   142: iload_1        
        //   143: aload_3        
        //   144: iconst_0       
        //   145: invokeinterface android/database/Cursor.getInt:(I)I
        //   150: iastore        
        //   151: aload_3        
        //   152: astore_2       
        //   153: aload           7
        //   155: iload_1        
        //   156: aload_3        
        //   157: iconst_1       
        //   158: invokeinterface android/database/Cursor.getString:(I)Ljava/lang/String;
        //   163: aastore        
        //   164: aload_3        
        //   165: astore_2       
        //   166: aload_3        
        //   167: invokeinterface android/database/Cursor.moveToNext:()Z
        //   172: pop            
        //   173: iload_1        
        //   174: iconst_1       
        //   175: iadd           
        //   176: istore_1       
        //   177: goto            129
        //   180: aload_3        
        //   181: astore_2       
        //   182: new             Landroid/content/ContentValues;
        //   185: dup            
        //   186: invokespecial   android/content/ContentValues.<init>:()V
        //   189: astore          7
        //   191: aload_3        
        //   192: astore_2       
        //   193: aload           7
        //   195: ldc             "calendar_id"
        //   197: aload           6
        //   199: iconst_0       
        //   200: iaload         
        //   201: invokestatic    java/lang/Integer.valueOf:(I)Ljava/lang/Integer;
        //   204: invokevirtual   android/content/ContentValues.put:(Ljava/lang/String;Ljava/lang/Integer;)V
        //   207: aload_3        
        //   208: astore_2       
        //   209: aload_0        
        //   210: getfield        com/admarvel/android/ads/r$d.d:Ljava/lang/String;
        //   213: ifnull          229
        //   216: aload_3        
        //   217: astore_2       
        //   218: aload           7
        //   220: ldc             "title"
        //   222: aload_0        
        //   223: getfield        com/admarvel/android/ads/r$d.d:Ljava/lang/String;
        //   226: invokevirtual   android/content/ContentValues.put:(Ljava/lang/String;Ljava/lang/String;)V
        //   229: aload_3        
        //   230: astore_2       
        //   231: aload_0        
        //   232: getfield        com/admarvel/android/ads/r$d.e:Ljava/lang/String;
        //   235: ifnull          251
        //   238: aload_3        
        //   239: astore_2       
        //   240: aload           7
        //   242: ldc             "description"
        //   244: aload_0        
        //   245: getfield        com/admarvel/android/ads/r$d.e:Ljava/lang/String;
        //   248: invokevirtual   android/content/ContentValues.put:(Ljava/lang/String;Ljava/lang/String;)V
        //   251: aload_3        
        //   252: astore_2       
        //   253: aload_0        
        //   254: getfield        com/admarvel/android/ads/r$d.f:Ljava/lang/String;
        //   257: ifnull          273
        //   260: aload_3        
        //   261: astore_2       
        //   262: aload           7
        //   264: ldc             "eventLocation"
        //   266: aload_0        
        //   267: getfield        com/admarvel/android/ads/r$d.f:Ljava/lang/String;
        //   270: invokevirtual   android/content/ContentValues.put:(Ljava/lang/String;Ljava/lang/String;)V
        //   273: aload_3        
        //   274: astore_2       
        //   275: aload_0        
        //   276: getfield        com/admarvel/android/ads/r$d.b:Ljava/lang/Long;
        //   279: ifnull          295
        //   282: aload_3        
        //   283: astore_2       
        //   284: aload           7
        //   286: ldc             "dtstart"
        //   288: aload_0        
        //   289: getfield        com/admarvel/android/ads/r$d.b:Ljava/lang/Long;
        //   292: invokevirtual   android/content/ContentValues.put:(Ljava/lang/String;Ljava/lang/Long;)V
        //   295: aload_3        
        //   296: astore_2       
        //   297: aload_0        
        //   298: getfield        com/admarvel/android/ads/r$d.c:Ljava/lang/Long;
        //   301: ifnull          317
        //   304: aload_3        
        //   305: astore_2       
        //   306: aload           7
        //   308: ldc             "dtend"
        //   310: aload_0        
        //   311: getfield        com/admarvel/android/ads/r$d.c:Ljava/lang/Long;
        //   314: invokevirtual   android/content/ContentValues.put:(Ljava/lang/String;Ljava/lang/Long;)V
        //   317: aload_3        
        //   318: astore_2       
        //   319: aload_0        
        //   320: getfield        com/admarvel/android/ads/r$d.g:Ljava/lang/String;
        //   323: ifnull          373
        //   326: aload_3        
        //   327: astore_2       
        //   328: aload_0        
        //   329: getfield        com/admarvel/android/ads/r$d.g:Ljava/lang/String;
        //   332: invokevirtual   java/lang/String.toLowerCase:()Ljava/lang/String;
        //   335: ldc             "true"
        //   337: invokevirtual   java/lang/String.equals:(Ljava/lang/Object;)Z
        //   340: ifne            360
        //   343: aload_3        
        //   344: astore_2       
        //   345: aload_0        
        //   346: getfield        com/admarvel/android/ads/r$d.g:Ljava/lang/String;
        //   349: invokevirtual   java/lang/String.toLowerCase:()Ljava/lang/String;
        //   352: ldc             "yes"
        //   354: invokevirtual   java/lang/String.equals:(Ljava/lang/Object;)Z
        //   357: ifeq            373
        //   360: aload_3        
        //   361: astore_2       
        //   362: aload           7
        //   364: ldc             "allDay"
        //   366: iconst_1       
        //   367: invokestatic    java/lang/Integer.valueOf:(I)Ljava/lang/Integer;
        //   370: invokevirtual   android/content/ContentValues.put:(Ljava/lang/String;Ljava/lang/Integer;)V
        //   373: aload_3        
        //   374: astore_2       
        //   375: aload_0        
        //   376: getfield        com/admarvel/android/ads/r$d.j:I
        //   379: ifgt            395
        //   382: aload_3        
        //   383: astore_2       
        //   384: aload           7
        //   386: ldc             "hasAlarm"
        //   388: iconst_1       
        //   389: invokestatic    java/lang/Integer.valueOf:(I)Ljava/lang/Integer;
        //   392: invokevirtual   android/content/ContentValues.put:(Ljava/lang/String;Ljava/lang/Integer;)V
        //   395: aload_3        
        //   396: astore_2       
        //   397: aload_0        
        //   398: getfield        com/admarvel/android/ads/r$d.h:Ljava/lang/String;
        //   401: ifnull          429
        //   404: aload_3        
        //   405: astore_2       
        //   406: aload_0        
        //   407: getfield        com/admarvel/android/ads/r$d.h:Ljava/lang/String;
        //   410: invokevirtual   java/lang/String.length:()I
        //   413: ifle            429
        //   416: aload_3        
        //   417: astore_2       
        //   418: aload           7
        //   420: ldc             "eventTimezone"
        //   422: aload_0        
        //   423: getfield        com/admarvel/android/ads/r$d.h:Ljava/lang/String;
        //   426: invokevirtual   android/content/ContentValues.put:(Ljava/lang/String;Ljava/lang/String;)V
        //   429: aload_3        
        //   430: astore_2       
        //   431: new             Ljava/lang/StringBuilder;
        //   434: dup            
        //   435: invokespecial   java/lang/StringBuilder.<init>:()V
        //   438: aload_0        
        //   439: invokevirtual   com/admarvel/android/ads/r$d.a:()Ljava/lang/String;
        //   442: invokevirtual   java/lang/StringBuilder.append:(Ljava/lang/String;)Ljava/lang/StringBuilder;
        //   445: ldc             "events"
        //   447: invokevirtual   java/lang/StringBuilder.append:(Ljava/lang/String;)Ljava/lang/StringBuilder;
        //   450: invokevirtual   java/lang/StringBuilder.toString:()Ljava/lang/String;
        //   453: invokestatic    android/net/Uri.parse:(Ljava/lang/String;)Landroid/net/Uri;
        //   456: astore          8
        //   458: aload_3        
        //   459: astore_2       
        //   460: new             Ljava/lang/StringBuilder;
        //   463: dup            
        //   464: invokespecial   java/lang/StringBuilder.<init>:()V
        //   467: aload_0        
        //   468: invokevirtual   com/admarvel/android/ads/r$d.a:()Ljava/lang/String;
        //   471: invokevirtual   java/lang/StringBuilder.append:(Ljava/lang/String;)Ljava/lang/StringBuilder;
        //   474: ldc             "reminders"
        //   476: invokevirtual   java/lang/StringBuilder.append:(Ljava/lang/String;)Ljava/lang/StringBuilder;
        //   479: invokevirtual   java/lang/StringBuilder.toString:()Ljava/lang/String;
        //   482: invokestatic    android/net/Uri.parse:(Ljava/lang/String;)Landroid/net/Uri;
        //   485: astore          6
        //   487: aload_3        
        //   488: astore_2       
        //   489: aload           4
        //   491: aload           8
        //   493: aload           7
        //   495: invokevirtual   android/content/ContentResolver.insert:(Landroid/net/Uri;Landroid/content/ContentValues;)Landroid/net/Uri;
        //   498: astore          7
        //   500: aload           7
        //   502: ifnull          650
        //   505: aload_3        
        //   506: astore_2       
        //   507: aload_0        
        //   508: getfield        com/admarvel/android/ads/r$d.j:I
        //   511: ifgt            589
        //   514: aload_3        
        //   515: astore_2       
        //   516: new             Landroid/content/ContentValues;
        //   519: dup            
        //   520: invokespecial   android/content/ContentValues.<init>:()V
        //   523: astore          8
        //   525: aload_3        
        //   526: astore_2       
        //   527: aload           8
        //   529: ldc             "event_id"
        //   531: aload           7
        //   533: invokevirtual   android/net/Uri.getLastPathSegment:()Ljava/lang/String;
        //   536: invokestatic    java/lang/Long.parseLong:(Ljava/lang/String;)J
        //   539: invokestatic    java/lang/Long.valueOf:(J)Ljava/lang/Long;
        //   542: invokevirtual   android/content/ContentValues.put:(Ljava/lang/String;Ljava/lang/Long;)V
        //   545: aload_3        
        //   546: astore_2       
        //   547: aload           8
        //   549: ldc             "method"
        //   551: iconst_1       
        //   552: invokestatic    java/lang/Integer.valueOf:(I)Ljava/lang/Integer;
        //   555: invokevirtual   android/content/ContentValues.put:(Ljava/lang/String;Ljava/lang/Integer;)V
        //   558: aload_3        
        //   559: astore_2       
        //   560: aload           8
        //   562: ldc             "minutes"
        //   564: aload_0        
        //   565: getfield        com/admarvel/android/ads/r$d.j:I
        //   568: invokestatic    java/lang/Math.abs:(I)I
        //   571: invokestatic    java/lang/Integer.valueOf:(I)Ljava/lang/Integer;
        //   574: invokevirtual   android/content/ContentValues.put:(Ljava/lang/String;Ljava/lang/Integer;)V
        //   577: aload_3        
        //   578: astore_2       
        //   579: aload           4
        //   581: aload           6
        //   583: aload           8
        //   585: invokevirtual   android/content/ContentResolver.insert:(Landroid/net/Uri;Landroid/content/ContentValues;)Landroid/net/Uri;
        //   588: pop            
        //   589: aload_3        
        //   590: astore_2       
        //   591: aload_0        
        //   592: getfield        com/admarvel/android/ads/r$d.i:Ljava/lang/String;
        //   595: ifnull          639
        //   598: aload_3        
        //   599: astore_2       
        //   600: aload_0        
        //   601: getfield        com/admarvel/android/ads/r$d.i:Ljava/lang/String;
        //   604: invokevirtual   java/lang/String.length:()I
        //   607: ifle            639
        //   610: aload_3        
        //   611: astore_2       
        //   612: aload           5
        //   614: new             Ljava/lang/StringBuilder;
        //   617: dup            
        //   618: invokespecial   java/lang/StringBuilder.<init>:()V
        //   621: aload_0        
        //   622: getfield        com/admarvel/android/ads/r$d.i:Ljava/lang/String;
        //   625: invokevirtual   java/lang/StringBuilder.append:(Ljava/lang/String;)Ljava/lang/StringBuilder;
        //   628: ldc             "(\"YES\")"
        //   630: invokevirtual   java/lang/StringBuilder.append:(Ljava/lang/String;)Ljava/lang/StringBuilder;
        //   633: invokevirtual   java/lang/StringBuilder.toString:()Ljava/lang/String;
        //   636: invokevirtual   com/admarvel/android/ads/d.e:(Ljava/lang/String;)V
        //   639: aload_3        
        //   640: ifnull          32
        //   643: aload_3        
        //   644: invokeinterface android/database/Cursor.close:()V
        //   649: return         
        //   650: aload_3        
        //   651: astore_2       
        //   652: aload_0        
        //   653: getfield        com/admarvel/android/ads/r$d.i:Ljava/lang/String;
        //   656: ifnull          639
        //   659: aload_3        
        //   660: astore_2       
        //   661: aload_0        
        //   662: getfield        com/admarvel/android/ads/r$d.i:Ljava/lang/String;
        //   665: invokevirtual   java/lang/String.length:()I
        //   668: ifle            639
        //   671: aload_3        
        //   672: astore_2       
        //   673: aload           5
        //   675: new             Ljava/lang/StringBuilder;
        //   678: dup            
        //   679: invokespecial   java/lang/StringBuilder.<init>:()V
        //   682: aload_0        
        //   683: getfield        com/admarvel/android/ads/r$d.i:Ljava/lang/String;
        //   686: invokevirtual   java/lang/StringBuilder.append:(Ljava/lang/String;)Ljava/lang/StringBuilder;
        //   689: ldc_w           "(\"NO\")"
        //   692: invokevirtual   java/lang/StringBuilder.append:(Ljava/lang/String;)Ljava/lang/StringBuilder;
        //   695: invokevirtual   java/lang/StringBuilder.toString:()Ljava/lang/String;
        //   698: invokevirtual   com/admarvel/android/ads/d.e:(Ljava/lang/String;)V
        //   701: goto            639
        //   704: astore          4
        //   706: aload_3        
        //   707: astore_2       
        //   708: aload_0        
        //   709: getfield        com/admarvel/android/ads/r$d.i:Ljava/lang/String;
        //   712: ifnull          757
        //   715: aload_3        
        //   716: astore_2       
        //   717: aload_0        
        //   718: getfield        com/admarvel/android/ads/r$d.i:Ljava/lang/String;
        //   721: invokevirtual   java/lang/String.length:()I
        //   724: ifle            757
        //   727: aload_3        
        //   728: astore_2       
        //   729: aload           5
        //   731: new             Ljava/lang/StringBuilder;
        //   734: dup            
        //   735: invokespecial   java/lang/StringBuilder.<init>:()V
        //   738: aload_0        
        //   739: getfield        com/admarvel/android/ads/r$d.i:Ljava/lang/String;
        //   742: invokevirtual   java/lang/StringBuilder.append:(Ljava/lang/String;)Ljava/lang/StringBuilder;
        //   745: ldc_w           "(\"NO\")"
        //   748: invokevirtual   java/lang/StringBuilder.append:(Ljava/lang/String;)Ljava/lang/StringBuilder;
        //   751: invokevirtual   java/lang/StringBuilder.toString:()Ljava/lang/String;
        //   754: invokevirtual   com/admarvel/android/ads/d.e:(Ljava/lang/String;)V
        //   757: aload_3        
        //   758: astore_2       
        //   759: aload           4
        //   761: invokevirtual   java/lang/Exception.printStackTrace:()V
        //   764: aload_3        
        //   765: ifnull          32
        //   768: aload_3        
        //   769: invokeinterface android/database/Cursor.close:()V
        //   774: return         
        //   775: astore_3       
        //   776: aconst_null    
        //   777: astore_2       
        //   778: aload_2        
        //   779: ifnull          788
        //   782: aload_2        
        //   783: invokeinterface android/database/Cursor.close:()V
        //   788: aload_3        
        //   789: athrow         
        //   790: astore_3       
        //   791: goto            778
        //   794: astore          4
        //   796: aconst_null    
        //   797: astore_3       
        //   798: goto            706
        //    Exceptions:
        //  Try           Handler
        //  Start  End    Start  End    Type                 
        //  -----  -----  -----  -----  ---------------------
        //  39     87     794    801    Ljava/lang/Exception;
        //  39     87     775    778    Any
        //  93     102    704    706    Ljava/lang/Exception;
        //  93     102    790    794    Any
        //  104    115    704    706    Ljava/lang/Exception;
        //  104    115    790    794    Any
        //  117    127    704    706    Ljava/lang/Exception;
        //  117    127    790    794    Any
        //  131    138    704    706    Ljava/lang/Exception;
        //  131    138    790    794    Any
        //  140    151    704    706    Ljava/lang/Exception;
        //  140    151    790    794    Any
        //  153    164    704    706    Ljava/lang/Exception;
        //  153    164    790    794    Any
        //  166    173    704    706    Ljava/lang/Exception;
        //  166    173    790    794    Any
        //  182    191    704    706    Ljava/lang/Exception;
        //  182    191    790    794    Any
        //  193    207    704    706    Ljava/lang/Exception;
        //  193    207    790    794    Any
        //  209    216    704    706    Ljava/lang/Exception;
        //  209    216    790    794    Any
        //  218    229    704    706    Ljava/lang/Exception;
        //  218    229    790    794    Any
        //  231    238    704    706    Ljava/lang/Exception;
        //  231    238    790    794    Any
        //  240    251    704    706    Ljava/lang/Exception;
        //  240    251    790    794    Any
        //  253    260    704    706    Ljava/lang/Exception;
        //  253    260    790    794    Any
        //  262    273    704    706    Ljava/lang/Exception;
        //  262    273    790    794    Any
        //  275    282    704    706    Ljava/lang/Exception;
        //  275    282    790    794    Any
        //  284    295    704    706    Ljava/lang/Exception;
        //  284    295    790    794    Any
        //  297    304    704    706    Ljava/lang/Exception;
        //  297    304    790    794    Any
        //  306    317    704    706    Ljava/lang/Exception;
        //  306    317    790    794    Any
        //  319    326    704    706    Ljava/lang/Exception;
        //  319    326    790    794    Any
        //  328    343    704    706    Ljava/lang/Exception;
        //  328    343    790    794    Any
        //  345    360    704    706    Ljava/lang/Exception;
        //  345    360    790    794    Any
        //  362    373    704    706    Ljava/lang/Exception;
        //  362    373    790    794    Any
        //  375    382    704    706    Ljava/lang/Exception;
        //  375    382    790    794    Any
        //  384    395    704    706    Ljava/lang/Exception;
        //  384    395    790    794    Any
        //  397    404    704    706    Ljava/lang/Exception;
        //  397    404    790    794    Any
        //  406    416    704    706    Ljava/lang/Exception;
        //  406    416    790    794    Any
        //  418    429    704    706    Ljava/lang/Exception;
        //  418    429    790    794    Any
        //  431    458    704    706    Ljava/lang/Exception;
        //  431    458    790    794    Any
        //  460    487    704    706    Ljava/lang/Exception;
        //  460    487    790    794    Any
        //  489    500    704    706    Ljava/lang/Exception;
        //  489    500    790    794    Any
        //  507    514    704    706    Ljava/lang/Exception;
        //  507    514    790    794    Any
        //  516    525    704    706    Ljava/lang/Exception;
        //  516    525    790    794    Any
        //  527    545    704    706    Ljava/lang/Exception;
        //  527    545    790    794    Any
        //  547    558    704    706    Ljava/lang/Exception;
        //  547    558    790    794    Any
        //  560    577    704    706    Ljava/lang/Exception;
        //  560    577    790    794    Any
        //  579    589    704    706    Ljava/lang/Exception;
        //  579    589    790    794    Any
        //  591    598    704    706    Ljava/lang/Exception;
        //  591    598    790    794    Any
        //  600    610    704    706    Ljava/lang/Exception;
        //  600    610    790    794    Any
        //  612    639    704    706    Ljava/lang/Exception;
        //  612    639    790    794    Any
        //  652    659    704    706    Ljava/lang/Exception;
        //  652    659    790    794    Any
        //  661    671    704    706    Ljava/lang/Exception;
        //  661    671    790    794    Any
        //  673    701    704    706    Ljava/lang/Exception;
        //  673    701    790    794    Any
        //  708    715    790    794    Any
        //  717    727    790    794    Any
        //  729    757    790    794    Any
        //  759    764    790    794    Any
        // 
        // The error that occurred was:
        // 
        // java.lang.IllegalStateException: Expression is linked from several locations: Label_0129:
        //     at com.strobel.decompiler.ast.Error.expressionLinkedFromMultipleLocations(Error.java:27)
        //     at com.strobel.decompiler.ast.AstOptimizer.mergeDisparateObjectInitializations(AstOptimizer.java:2604)
        //     at com.strobel.decompiler.ast.AstOptimizer.optimize(AstOptimizer.java:235)
        //     at com.strobel.decompiler.ast.AstOptimizer.optimize(AstOptimizer.java:42)
        //     at com.strobel.decompiler.languages.java.ast.AstMethodBodyBuilder.createMethodBody(AstMethodBodyBuilder.java:209)
        //     at com.strobel.decompiler.languages.java.ast.AstMethodBodyBuilder.createMethodBody(AstMethodBodyBuilder.java:94)
        //     at com.strobel.decompiler.languages.java.ast.AstBuilder.createMethodBody(AstBuilder.java:840)
        //     at com.strobel.decompiler.languages.java.ast.AstBuilder.createMethod(AstBuilder.java:733)
        //     at com.strobel.decompiler.languages.java.ast.AstBuilder.addTypeMembers(AstBuilder.java:610)
        //     at com.strobel.decompiler.languages.java.ast.AstBuilder.createTypeCore(AstBuilder.java:577)
        //     at com.strobel.decompiler.languages.java.ast.AstBuilder.createTypeNoCache(AstBuilder.java:193)
        //     at com.strobel.decompiler.languages.java.ast.AstBuilder.createType(AstBuilder.java:160)
        //     at com.strobel.decompiler.languages.java.ast.AstBuilder.addType(AstBuilder.java:135)
        //     at com.strobel.decompiler.languages.java.JavaLanguage.buildAst(JavaLanguage.java:71)
        //     at com.strobel.decompiler.languages.java.JavaLanguage.decompileType(JavaLanguage.java:59)
        //     at com.strobel.decompiler.DecompilerDriver.decompileType(DecompilerDriver.java:333)
        //     at com.strobel.decompiler.DecompilerDriver.decompileJar(DecompilerDriver.java:254)
        //     at com.strobel.decompiler.DecompilerDriver.main(DecompilerDriver.java:144)
        // 
        throw new IllegalStateException("An error occurred while decompiling this method.");
    }
}
